.gitignore
.pre-commit-config.yaml
.pylintrc
.readthedocs.yml
CODE_OF_CONDUCT.md
LICENSE
README.rst
README.rst.license
community_tca9555.py
pyproject.toml
requirements.txt
setup.py
.github/workflows/build.yml
.github/workflows/failure-help-text.yml
.github/workflows/release.yml
LICENSES/CC-BY-4.0.txt
LICENSES/MIT.txt
LICENSES/Unlicense.txt
community_circuitpython_tca9555.egg-info/PKG-INFO
community_circuitpython_tca9555.egg-info/SOURCES.txt
community_circuitpython_tca9555.egg-info/dependency_links.txt
community_circuitpython_tca9555.egg-info/requires.txt
community_circuitpython_tca9555.egg-info/top_level.txt
docs/api.rst
docs/api.rst.license
docs/conf.py
docs/examples.rst
docs/examples.rst.license
docs/index.rst
docs/index.rst.license
docs/_static/favicon.ico
docs/_static/favicon.ico.license
examples/tca9555_debounce_inputs.py
examples/tca9555_pimoroni_rgb_base.py
examples/tca9555_simpletest.py