Metadata-Version: 2.1
Name: community-circuitpython-tca9555
Version: 0.2.2
Summary: CircuitPython library for connecting a TCA9555 16-Bit I2C GPIO expander
Home-page: https://github.com/lesamouraipourpre/Community_CircuitPython_TCA9555.git
Author: James Carr
Author-email: 
License: MIT
Keywords: adafruit blinka circuitpython micropython tca9555 i2c gpio expander hardware pimoroni pico_rgb_base
Platform: UNKNOWN
Classifier: Development Status :: 3 - Alpha
Classifier: Intended Audience :: Developers
Classifier: Topic :: Software Development :: Libraries
Classifier: Topic :: System :: Hardware
Classifier: License :: OSI Approved :: MIT License
Classifier: Programming Language :: Python :: 3
Classifier: Programming Language :: Python :: 3.4
Classifier: Programming Language :: Python :: 3.5
